super_taxi/__init__.py
super_taxi/__main__.py
super_taxi/taxi_system.py
super_taxi/api/booking_api.py
super_taxi/controllers/booking.py
super_taxi/controllers/registration.py
super_taxi/core/clock.py
super_taxi/core/functions.py
super_taxi/core/ride_handler.py
super_taxi/core/taxi_grid.py
super_taxi/core/taxi_manager.py
super_taxi/model/buses.py
super_taxi/model/cars.py
super_taxi/model/generics.py
super_taxi/model/grid.py
super_taxi/model/rides.py
super_taxi/model/taxis.py
test/__init__.py
test/test_booking.py
test/test_functions.py
test/test_grid.py
test/test_ride_handler.py
test/test_taxi_manager.py
super_taxi_api-0.0.3.dist-info/LICENSE
super_taxi_api-0.0.3.dist-info/METADATA
super_taxi_api-0.0.3.dist-info/WHEEL
super_taxi_api-0.0.3.dist-info/entry_points.txt
super_taxi_api-0.0.3.dist-info/top_level.txt
super_taxi_api-0.0.3.dist-info/RECORD
