Metadata-Version: 2.1
Name: super-taxi-api
Version: 0.0.3
Summary: Simple taxi booking api
Home-page: https://github.com/sanjayatb/taxi-booking-system
Author: Sanjaya Bandara
Author-email: arstbandara@gmail.com
License: UNKNOWN
Keywords: Taxi,booking
Platform: UNKNOWN
Classifier: Programming Language :: Python
Classifier: Programming Language :: Python :: 3
Classifier: Programming Language :: Python :: 3 :: Only
Classifier: Development Status :: 5 - Production/Stable
Classifier: Environment :: Console
Classifier: Intended Audience :: Developers
Classifier: License :: OSI Approved :: BSD License
Classifier: Operating System :: OS Independent
Classifier: Topic :: Internet :: WWW/HTTP :: Indexing/Search
Classifier: Topic :: Software Development :: Libraries :: Python Modules
Classifier: Topic :: Text Processing
Classifier: Topic :: Internet :: WWW/HTTP
Requires-Python: >=3.6
Requires-Dist: flask
Requires-Dist: requests
Provides-Extra: dev
Requires-Dist: pytest (>=3.7) ; extra == 'dev'
